hypersphere_sampler/__init__.py
hypersphere_sampler/sampler.py
hypersphere_sampler-0.1.1.dist-info/licenses/LICENSE
hypersphere_sampler-0.1.1.dist-info/METADATA
hypersphere_sampler-0.1.1.dist-info/WHEEL
hypersphere_sampler-0.1.1.dist-info/top_level.txt
hypersphere_sampler-0.1.1.dist-info/RECORD
