Metadata-Version: 2.4
Name: hypersphere-sampler
Version: 0.1.1
Summary: A Python package for sampling points on or inside hyperspheres and hyperellipsoids.
Author: Andreas Nygaard
License: MIT License
Project-URL: Homepage, https://github.com/AndreasNygaard/hypersphere-sampler
Project-URL: Repository, https://github.com/AndreasNygaard/hypersphere-sampler
Requires-Python: >=3.6
License-File: LICENSE
Requires-Dist: numpy
Dynamic: license-file
